volttron/driver/interfaces/modbus_tk/__init__.py
volttron/driver/interfaces/modbus_tk/modbus_tk.py
volttron/driver/interfaces/modbus_tk/utils/__init__.py
volttron/driver/interfaces/modbus_tk/utils/client.py
volttron/driver/interfaces/modbus_tk/utils/config_cmd.py
volttron/driver/interfaces/modbus_tk/utils/helpers.py
volttron/driver/interfaces/modbus_tk/utils/maps/__init__.py
volttron/driver/interfaces/modbus_tk/utils/maps/battery_meter.csv
volttron/driver/interfaces/modbus_tk/utils/maps/ion6200.config
volttron/driver/interfaces/modbus_tk/utils/maps/ion6200.csv
volttron/driver/interfaces/modbus_tk/utils/maps/ion6200_map.csv
volttron/driver/interfaces/modbus_tk/utils/maps/ion8600.csv
volttron/driver/interfaces/modbus_tk/utils/maps/ion8600_map.csv
volttron/driver/interfaces/modbus_tk/utils/maps/maps.yaml
volttron/driver/interfaces/modbus_tk/utils/maps/mixed_endian_reg_map.csv
volttron/driver/interfaces/modbus_tk/utils/maps/modbus_tk_test.config
volttron/driver/interfaces/modbus_tk/utils/maps/modbus_tk_test.csv
volttron/driver/interfaces/modbus_tk/utils/maps/modbus_tk_test_map.csv
volttron/driver/interfaces/modbus_tk/utils/maps/scale_reg_map.csv
volttron/driver/interfaces/modbus_tk/utils/maps/scale_reg_pow_10_map.csv
volttron/driver/interfaces/modbus_tk/utils/maps/watts_on.config
volttron/driver/interfaces/modbus_tk/utils/maps/watts_on.csv
volttron/driver/interfaces/modbus_tk/utils/maps/watts_on_map.csv
volttron/driver/interfaces/modbus_tk/utils/maps/write_single_registers.config
volttron/driver/interfaces/modbus_tk/utils/maps/write_single_registers.csv
volttron/driver/interfaces/modbus_tk/utils/maps/write_single_registers_map.csv
volttron/driver/interfaces/modbus_tk/utils/maps.py
volttron/driver/interfaces/modbus_tk/utils/server.py
volttron_lib_modbustk_driver-0.1.2rc0.dist-info/LICENSE
volttron_lib_modbustk_driver-0.1.2rc0.dist-info/METADATA
volttron_lib_modbustk_driver-0.1.2rc0.dist-info/WHEEL
volttron_lib_modbustk_driver-0.1.2rc0.dist-info/RECORD
