Metadata-Version: 2.1
Name: volttron-lib-modbustk-driver
Version: 0.1.2rc0
Summary: ModbusTK Driver supported and maintained by the Volttron team.
Home-page: https://github.com/VOLTTRON/volttron-drivers/volttron-lib-modbustk-driver
License: Apache-2.0
Author: Mark Bonicillo
Author-email: volttron@pnnl.gov
Requires-Python: >=3.10,<4.0
Classifier: Intended Audience :: Developers
Classifier: Intended Audience :: Information Technology
Classifier: Intended Audience :: Other Audience
Classifier: Intended Audience :: Science/Research
Classifier: License :: OSI Approved :: Apache Software License
Classifier: Programming Language :: Python :: 3
Classifier: Programming Language :: Python :: 3.10
Classifier: Programming Language :: Python :: 3.11
Classifier: Programming Language :: Python :: 3 :: Only
Requires-Dist: PyYAML (>=6.0,<7.0)
Requires-Dist: modbus-tk (>=1.1.3,<2.0.0)
Requires-Dist: pyserial (>=3.5,<4.0)
Requires-Dist: volttron-lib-base-driver (>=0.2.1rc2,<0.3.0)
Project-URL: Repository, https://github.com/VOLTTRON/volttron-lib-modbustk-driver
